zndraw_utils/__init__.py
zndraw_utils/base.py
zndraw_utils/cli.py
zndraw_utils/md.py
zndraw_utils/relax.py
zndraw_utils/smiles.py
zndraw_utils/solvate.py
zndraw_utils/utils.py
zndraw_utils-0.1.0.dist-info/METADATA
zndraw_utils-0.1.0.dist-info/WHEEL
zndraw_utils-0.1.0.dist-info/entry_points.txt
zndraw_utils-0.1.0.dist-info/RECORD
